walmartBot/__init__.py
walmartbot-0.0.3.dist-info/licenses/LICENSE
walmartbot-0.0.3.dist-info/METADATA
walmartbot-0.0.3.dist-info/WHEEL
walmartbot-0.0.3.dist-info/top_level.txt
walmartbot-0.0.3.dist-info/RECORD
