Metadata-Version: 2.4
Name: walmartBot
Version: 0.0.3
Summary: retail-bot-research
Home-page: https://www.jiangongfang.top
Author: Xiaomu
Author-email: jiangongfang@foxmail.com
License: MIT
Classifier: Programming Language :: Python :: 3.8
Classifier: Programming Language :: Python :: 3.9
Classifier: Programming Language :: Python :: 3.10
Classifier: Programming Language :: Python :: 3.11
Classifier: Programming Language :: Python :: 3.12
Classifier: Programming Language :: Python :: 3.13
Classifier: License :: OSI Approved :: MIT License
Classifier: Operating System :: OS Independent
Requires-Python: <=3.13
License-File: LICENSE
Requires-Dist: setuptools
Requires-Dist: requests
Requires-Dist: PySocks
Requires-Dist: curl_cffi>=0.13.0
Dynamic: author
Dynamic: author-email
Dynamic: classifier
Dynamic: description
Dynamic: description-content-type
Dynamic: home-page
Dynamic: license
Dynamic: license-file
Dynamic: requires-dist
Dynamic: requires-python
Dynamic: summary
